DeepWon/__init__.py
DeepWon/callbacks/__init__.py
DeepWon/callbacks/callbacks.py
DeepWon/layers/__init__.py
DeepWon/layers/layers.py
DeepWon/losses/__init__.py
DeepWon/losses/gan_loss.py
DeepWon/models/__init__.py
DeepWon/models/models.py
DeepWon/optimizers/__init__.py
DeepWon/optimizers/optimizers.py
DeepWon/preprocess/__init__.py
DeepWon/schedulers/__init__.py
DeepWon/schedulers/schedulers.py
DeepWon/utils/__init__.py
DeepWon/utils/utils.py
DeepWon-0.6.dist-info/METADATA
DeepWon-0.6.dist-info/WHEEL
DeepWon-0.6.dist-info/top_level.txt
DeepWon-0.6.dist-info/RECORD
