Metadata-Version: 2.1
Name: DeepWon
Version: 0.6
Summary: Deep Learning utilities written in Tensorflow 2.0
Home-page: https://github.com/three0-s/DeepWon
Author: Lim Yewon
Author-email: ga06033@gmail.com
License: UNKNOWN
Keywords: Deep Learning,DL,Tensorflow,Keras
Platform: UNKNOWN
Classifier: Programming Language :: Python :: 3
Classifier: Programming Language :: Python :: 3.2
Classifier: Programming Language :: Python :: 3.3
Classifier: Programming Language :: Python :: 3.4
Classifier: Programming Language :: Python :: 3.5
Classifier: Programming Language :: Python :: 3.6
Classifier: Programming Language :: Python :: 3.7
Requires-Python: >=3
Requires-Dist: tensorflow
Requires-Dist: tensorflow-addons
Requires-Dist: numpy
Requires-Dist: matplotlib
Requires-Dist: sklearn
